nendo_plugin_musicgen/__init__.py
nendo_plugin_musicgen/config.py
nendo_plugin_musicgen/musicgen.py
nendo_plugin_musicgen/plugin.py
nendo_plugin_musicgen-0.1.6.dist-info/LICENSE
nendo_plugin_musicgen-0.1.6.dist-info/METADATA
nendo_plugin_musicgen-0.1.6.dist-info/WHEEL
nendo_plugin_musicgen-0.1.6.dist-info/RECORD
